Sequence Detector/SD.v
`timescale 1ps/1ps
module SD (
    input clk, rst_n, x, output z
);
    parameter A = 2'b00;
    parameter B = 2'b01;
    parameter C = 2'b10;
    parameter D = 2'b11;
    reg[1:0] state,next_state;

    always @(posedge clk, negedge rst_n) begin
        if(!rst_n)
        begin
            state <= A;
        end
        else
        begin
            state <= next_state;
        end
    end

    always @(*) begin
        case (state)
            A: begin
                if (x==0) begin
                    next_state = A;
                end
                else begin
                    next_state = B;
                end
            end 
            B: begin
                if (x==0) next_state = C;
                else next_state = B;
            end
            C: begin
                if(x==0) next_state = A;
                else next_state = D;
            end
            D: begin
                if (x==0) next_state = C;
                else next_state = B;
            end
            default: next_state = A;
        endcase
    end
    assign z = (state==D && x==0)?1:0;
endmodule

Sequence Detector/SD_test.v
`timescale 1ps/1ps
module SD_test ();
    reg clk,rst_n,x;
    wire z;
    always #5 clk = ~clk;
    SD DUT(.clk(clk),.rst_n(rst_n),.x(x),.z(z));
    initial begin
        $dumpfile("example.vcd");
        $dumpvars(0,SD_test);
        $monitor($time," Z = %b", z);
        rst_n = 0; x=0; clk=0;
            #7 rst_n = 1;  // not on clock edge
        @(negedge clk); x = 1;
        @(negedge clk); x = 0;
        @(negedge clk); x = 1;
        @(negedge clk); x = 0;
        #10 $finish;
    end
endmodule

example.vcd
$date
	Wed Feb 25 00:56:16 2026
$end
$version
	Icarus Verilog
$end
$timescale
	1ps
$end
$scope module SD_test $end
$var wire 1 ! z $end
$var reg 1 " clk $end
$var reg 1 # rst_n $end
$var reg 1 $ x $end
$scope module DUT $end
$var wire 1 " clk $end
$var wire 1 # rst_n $end
$var wire 1 $ x $end
$var wire 1 ! z $end
$var parameter 2 % A $end
$var parameter 2 & B $end
$var parameter 2 ' C $end
$var parameter 2 ( D $end
$var reg 2 ) next_state [1:0] $end
$var reg 2 * state [1:0] $end
$upscope $end
$upscope $end
$enddefinitions $end
$comment Show the parameter values. $end
$dumpall
b11 (
b10 '
b1 &
b0 %
$end
#0
$dumpvars
b0 *
b0 )
0$
0#
1"
0!
$end
#5
0"
#7
1#
#10
1"
#15
b1 )
1$
0"
#20
b1 *
1"
#25
b10 )
0$
0"
#30
b0 )
b10 *
1"
#35
b11 )
1$
0"
#40
b1 )
b11 *
1"
#45
1!
b10 )
0$
0"
#50
0!
b0 )
b10 *
1"
