mul.v
// -------------------- PIPO1 --------------------
module PIPO1 (dout, din, ld, clk);
  input [15:0] din;
  input ld, clk;
  output reg [15:0] dout;

  always @(posedge clk)
    if (ld) dout <= din;
endmodule


// -------------------- PIPO2 --------------------
module PIPO2 (dout, din, ld, clr, clk);
  input [15:0] din;
  input ld, clr, clk;
  output reg [15:0] dout;

  always @(posedge clk)
    if (clr) dout <= 16'b0;
    else if (ld) dout <= din;
endmodule


// -------------------- ADD --------------------
module ADD (out, in1, in2);
  input [15:0] in1, in2;
  output reg [15:0] out;

  always @(*) out = in1 + in2;
endmodule


// -------------------- EQZ --------------------
module EQZ (eqz, data);
  input [15:0] data;
  output eqz;

  assign eqz = (data == 0);
endmodule


// -------------------- CNTR --------------------
module CNTR (dout, din, ld, dec, clk);
  input [15:0] din;
  input ld, dec, clk;
  output reg [15:0] dout;

  always @(posedge clk)
    if (ld) dout <= din;
    else if (dec) dout <= dout - 1;
endmodule


// -------------------- MUL DATAPATH --------------------
module MUL_datapath (eqz, LdA, LdB, LdP, clrP, decB, data_in, clk);
  input LdA, LdB, LdP, clrP, decB, clk;
  input [15:0] data_in;
  output eqz;

  wire [15:0] X, Y, Z, Bout, Bus;

  assign Bus = data_in;

  PIPO1 A (X, Bus, LdA, clk);
  PIPO2 P (Y, Z, LdP, clrP, clk);
  CNTR  B (Bout, Bus, LdB, decB, clk);
  ADD   AD (Z, X, Y);
  EQZ   COMP (eqz, Bout);
endmodule


// -------------------- CONTROLLER --------------------
module controller (LdA, LdB, LdP, clrP, decB, done, clk, eqz, start);
  input clk, eqz, start;
  output reg LdA, LdB, LdP, clrP, decB, done;

  reg [2:0] state;
  parameter S0=3'b000, S1=3'b001, S2=3'b010, S3=3'b011, S4=3'b100;

  initial state = S0;

  // FSM
  always @(posedge clk) begin
    case (state)
      S0: if (start) state <= S1;
      S1: state <= S2;
      S2: state <= S3;
      S3: if (eqz) state <= S4;
      S4: state <= S4;
      default: state <= S0;
    endcase
  end
  
  // Control signals
  always @(*) begin
  LdA = 0; LdB = 0; LdP = 0;
  clrP = 0; decB = 0; done = 0;

  case (state)
    S1: LdA = 1;

    S2: begin
      LdB = 1;
      clrP = 1;
    end

    S3: begin
      if (!eqz) begin
        LdP = 1;
        decB = 1;
      end
    end

    S4: done = 1;
  endcase
end

endmodule


// -------------------- TESTBENCH --------------------
module MUL_test;
  reg [15:0] data_in;
  reg clk, start;
  wire done, eqz;
  wire LdA, LdB, LdP, clrP, decB;

  MUL_datapath DP (eqz, LdA, LdB, LdP, clrP, decB, data_in, clk);
  controller    CON (LdA, LdB, LdP, clrP, decB, done, clk, eqz, start);

  initial begin
    clk = 0;
    start = 0;
    #5  start = 1;          // aligned with clock
    #200 $finish;
  end

  initial begin
    #15 data_in = 17;
    #10 data_in = 5;
  end

  always #5 clk = ~clk;

  initial begin
    $monitor("%0t\t%d\t%b", $time, DP.Y, done);
    $dumpfile("mul.vcd");
    $dumpvars(0, MUL_test);
  end
endmodule

mul.vcd
$date
	Thu Dec 25 14:39:13 2025
$end
$version
	Icarus Verilog
$end
$timescale
	1s
$end
$scope module MUL_test $end
$var wire 1 ! eqz $end
$var wire 1 " done $end
$var wire 1 # decB $end
$var wire 1 $ clrP $end
$var wire 1 % LdP $end
$var wire 1 & LdB $end
$var wire 1 ' LdA $end
$var reg 1 ( clk $end
$var reg 16 ) data_in [15:0] $end
$var reg 1 * start $end
$scope module CON $end
$var wire 1 ( clk $end
$var wire 1 * start $end
$var wire 1 ! eqz $end
$var parameter 3 + S0 $end
$var parameter 3 , S1 $end
$var parameter 3 - S2 $end
$var parameter 3 . S3 $end
$var parameter 3 / S4 $end
$var reg 1 ' LdA $end
$var reg 1 & LdB $end
$var reg 1 % LdP $end
$var reg 1 $ clrP $end
$var reg 1 # decB $end
$var reg 1 " done $end
$var reg 3 0 state [2:0] $end
$upscope $end
$scope module DP $end
$var wire 16 1 Bus [15:0] $end
$var wire 1 ' LdA $end
$var wire 1 & LdB $end
$var wire 1 % LdP $end
$var wire 1 ( clk $end
$var wire 1 $ clrP $end
$var wire 16 2 data_in [15:0] $end
$var wire 1 # decB $end
$var wire 1 ! eqz $end
$var wire 16 3 Z [15:0] $end
$var wire 16 4 Y [15:0] $end
$var wire 16 5 X [15:0] $end
$var wire 16 6 Bout [15:0] $end
$scope module A $end
$var wire 1 ( clk $end
$var wire 16 7 din [15:0] $end
$var wire 1 ' ld $end
$var reg 16 8 dout [15:0] $end
$upscope $end
$scope module AD $end
$var wire 16 9 in1 [15:0] $end
$var wire 16 : in2 [15:0] $end
$var reg 16 ; out [15:0] $end
$upscope $end
$scope module B $end
$var wire 1 ( clk $end
$var wire 1 # dec $end
$var wire 16 < din [15:0] $end
$var wire 1 & ld $end
$var reg 16 = dout [15:0] $end
$upscope $end
$scope module COMP $end
$var wire 16 > data [15:0] $end
$var wire 1 ! eqz $end
$upscope $end
$scope module P $end
$var wire 1 ( clk $end
$var wire 1 $ clr $end
$var wire 16 ? din [15:0] $end
$var wire 1 % ld $end
$var reg 16 @ dout [15:0] $end
$upscope $end
$upscope $end
$upscope $end
$enddefinitions $end
$comment Show the parameter values. $end
$dumpall
b100 /
b11 .
b10 -
b1 ,
b0 +
$end
#0
$dumpvars
bx @
bx ?
bx >
bx =
bx <
bx ;
bx :
bx 9
bx 8
bx 7
bx 6
bx 5
bx 4
bx 3
bx 2
bx 1
b0 0
0*
bx )
0(
0'
0&
0%
0$
0#
0"
x!
$end
#5
1'
b1 0
1(
1*
#10
0(
#15
1$
1&
0'
b10 0
b10001 5
b10001 8
b10001 9
1(
b10001 1
b10001 7
b10001 <
b10001 )
b10001 2
#20
0(
#25
b10001 3
b10001 ;
b10001 ?
1#
1%
0$
0&
b0 4
b0 :
b0 @
0!
b101 6
b101 =
b101 >
b11 0
1(
b101 1
b101 7
b101 <
b101 )
b101 2
#30
0(
#35
b100010 3
b100010 ;
b100010 ?
b100 6
b100 =
b100 >
b10001 4
b10001 :
b10001 @
1(
#40
0(
#45
b110011 3
b110011 ;
b110011 ?
b100010 4
b100010 :
b100010 @
b11 6
b11 =
b11 >
1(
#50
0(
#55
b1000100 3
b1000100 ;
b1000100 ?
b10 6
b10 =
b10 >
b110011 4
b110011 :
b110011 @
1(
#60
0(
#65
b1010101 3
b1010101 ;
b1010101 ?
b1000100 4
b1000100 :
b1000100 @
b1 6
b1 =
b1 >
1(
#70
0(
#75
0#
0%
b1100110 3
b1100110 ;
b1100110 ?
1!
b0 6
b0 =
b0 >
b1010101 4
b1010101 :
b1010101 @
1(
#80
0(
#85
1"
b100 0
1(
