StickyBit/stickybit.v
`timescale 1ps/1ps
module stickybit(
    input clk,rst_n,d,output z
);
    parameter S0 = 1'b0,S1 = 1'b1;
    reg s,ns;
    always @(posedge clk or negedge rst_n) begin
        if (!rst_n) begin
            s <= S1;
        end
        else s <= ns;
    end
    always @(*) begin
        case (s)
            S0: begin ns = S0; z = 0; end
            S1:begin
                if (d) begin
                    ns = S1; z=1;
                end
                else begin ns = S0; z=0; end
            end
            default: ns = S1;
        endcase
    end
endmodule

StickyBit/tb.v
`timescale 1ps/1ps
module tb();
    reg clk, rst_n, d;
    wire z;
    stickybit DUT(.clk(clk),.rst_n(rst_n),.d(d),.z(z));
    always #5 clk=~clk;
    initial begin
        $dumpfile("example.vcd");
        $dumpvars(0,tb);
        $monitor($time," Z = %b",z);
        clk = 0; rst_n = 0; d = 1;
        #7 rst_n = 1;
        @(negedge clk); d = 0;
        @(negedge clk); d = 0;
        @(negedge clk); d = 1;
        @(negedge clk); d = 0;
        @(negedge clk); d = 1;
        @(negedge clk); d = 0;
        @(negedge clk); d = 0; rst_n = 1;
        #3 rst_n = 0;
        @(negedge clk); d = 1;
        @(negedge clk); d = 0;
        #10 $finish;
    end
endmodule

StickyBit/example.vcd
$date
	Wed Feb 25 03:07:04 2026
$end
$version
	Icarus Verilog
$end
$timescale
	1ps
$end
$scope module tb $end
$var wire 1 ! z $end
$var reg 1 " clk $end
$var reg 1 # d $end
$var reg 1 $ rst_n $end
$scope module DUT $end
$var wire 1 " clk $end
$var wire 1 # d $end
$var wire 1 $ rst_n $end
$var wire 1 ! z $end
$var parameter 1 % S0 $end
$var parameter 1 & S1 $end
$var reg 1 ' ns $end
$var reg 1 ( s $end
$upscope $end
$upscope $end
$enddefinitions $end
$comment Show the parameter values. $end
$dumpall
1&
0%
$end
#0
$dumpvars
1(
1'
0$
1#
0"
0!
$end
#5
1"
#7
1$
#10
0'
0#
0"
#15
1!
0(
1"
#20
0"
#25
1"
#30
1#
0"
#35
1"
#40
0#
0"
#45
1"
#50
1#
0"
#55
1"
#60
0#
0"
#65
1"
#70
0"
#73
0!
1(
0$
#75
1"
#80
1'
1#
0"
#85
1"
#90
0'
0#
0"
