Lec31/regbank_v4.v
// 32 x 32 Register File with synchronous write and async read
module regbank_v4 (
    output [31:0] rdData1,
    output [31:0] rdData2,
    input  [31:0] wrData,
    input  [4:0]  sr1, sr2, dr,
    input  write,
    input  reset,
    input  clk
);

    reg [31:0] regfile [0:31];
    integer k;

    // Asynchronous read
    assign rdData1 = regfile[sr1];
    assign rdData2 = regfile[sr2];

    // Synchronous write + reset
    always @(posedge clk) begin
        if (reset) begin
            for (k = 0; k < 32; k = k + 1)
                regfile[k] <= 32'b0;
        end
        else if (write) begin
            regfile[dr] <= wrData;
        end
    end

endmodule

Lec31/regfile_test.v
module regfile_test;

    reg  [4:0] sr1, sr2, dr;
    reg  [31:0] wrData;
    reg  write, reset, clk;
    wire [31:0] rdData1, rdData2;
    integer k;

    regbank_v4 DUT (
        .rdData1(rdData1),
        .rdData2(rdData2),
        .wrData(wrData),
        .sr1(sr1),
        .sr2(sr2),
        .dr(dr),
        .write(write),
        .reset(reset),
        .clk(clk)
    );

    // Clock generation
    initial clk = 0;
    always #5 clk = ~clk;

    initial begin
        $dumpfile("regfile.vcd");
        $dumpvars(0, regfile_test);

        // Reset
        reset = 1; write = 0;
        #10 reset = 0;

        // WRITE PHASE
        for (k = 0; k < 32; k = k + 1) begin
            dr = k;
            wrData = k * 10;
            write = 1;
            #10;
        end
        write = 0;

        // READ PHASE
        for (k = 0; k < 32; k = k + 2) begin
            sr1 = k;
            sr2 = k + 1;
            #5;
            $display("reg[%0d] = %0d , reg[%0d] = %0d",
                     sr1, rdData1, sr2, rdData2);
        end

        #50 $finish;
    end
endmodule

Lec31/regfile.vcd
$date
	Mon Dec 29 17:25:26 2025
$end
$version
	Icarus Verilog
$end
$timescale
	1s
$end
$scope module regfile_test $end
$var wire 32 ! rdData2 [31:0] $end
$var wire 32 " rdData1 [31:0] $end
$var reg 1 # clk $end
$var reg 5 $ dr [4:0] $end
$var reg 1 % reset $end
$var reg 5 & sr1 [4:0] $end
$var reg 5 ' sr2 [4:0] $end
$var reg 32 ( wrData [31:0] $end
$var reg 1 ) write $end
$var integer 32 * k [31:0] $end
$scope module DUT $end
$var wire 1 # clk $end
$var wire 5 + dr [4:0] $end
$var wire 32 , rdData1 [31:0] $end
$var wire 32 - rdData2 [31:0] $end
$var wire 1 % reset $end
$var wire 5 . sr1 [4:0] $end
$var wire 5 / sr2 [4:0] $end
$var wire 32 0 wrData [31:0] $end
$var wire 1 ) write $end
$var integer 32 1 k [31:0] $end
$upscope $end
$upscope $end
$enddefinitions $end
$comment Show the parameter values. $end
$dumpall
$end
#0
$dumpvars
bx 1
bx 0
bx /
bx .
bx -
bx ,
bx +
bx *
0)
bx (
bx '
bx &
1%
bx $
0#
bx "
bx !
$end
#5
b100000 1
1#
#10
0#
1)
b0 (
b0 0
b0 $
b0 +
b0 *
0%
#15
1#
#20
0#
b1010 (
b1010 0
b1 $
b1 +
b1 *
#25
1#
#30
0#
b10100 (
b10100 0
b10 $
b10 +
b10 *
#35
1#
#40
0#
b11110 (
b11110 0
b11 $
b11 +
b11 *
#45
1#
#50
0#
b101000 (
b101000 0
b100 $
b100 +
b100 *
#55
1#
#60
0#
b110010 (
b110010 0
b101 $
b101 +
b101 *
#65
1#
#70
0#
b111100 (
b111100 0
b110 $
b110 +
b110 *
#75
1#
#80
0#
b1000110 (
b1000110 0
b111 $
b111 +
b111 *
#85
1#
#90
0#
b1010000 (
b1010000 0
b1000 $
b1000 +
b1000 *
#95
1#
#100
0#
b1011010 (
b1011010 0
b1001 $
b1001 +
b1001 *
#105
1#
#110
0#
b1100100 (
b1100100 0
b1010 $
b1010 +
b1010 *
#115
1#
#120
0#
b1101110 (
b1101110 0
b1011 $
b1011 +
b1011 *
#125
1#
#130
0#
b1111000 (
b1111000 0
b1100 $
b1100 +
b1100 *
#135
1#
#140
0#
b10000010 (
b10000010 0
b1101 $
b1101 +
b1101 *
#145
1#
#150
0#
b10001100 (
b10001100 0
b1110 $
b1110 +
b1110 *
#155
1#
#160
0#
b10010110 (
b10010110 0
b1111 $
b1111 +
b1111 *
#165
1#
#170
0#
b10100000 (
b10100000 0
b10000 $
b10000 +
b10000 *
#175
1#
#180
0#
b10101010 (
b10101010 0
b10001 $
b10001 +
b10001 *
#185
1#
#190
0#
b10110100 (
b10110100 0
b10010 $
b10010 +
b10010 *
#195
1#
#200
0#
b10111110 (
b10111110 0
b10011 $
b10011 +
b10011 *
#205
1#
#210
0#
b11001000 (
b11001000 0
b10100 $
b10100 +
b10100 *
#215
1#
#220
0#
b11010010 (
b11010010 0
b10101 $
b10101 +
b10101 *
#225
1#
#230
0#
b11011100 (
b11011100 0
b10110 $
b10110 +
b10110 *
#235
1#
#240
0#
b11100110 (
b11100110 0
b10111 $
b10111 +
b10111 *
#245
1#
#250
0#
b11110000 (
b11110000 0
b11000 $
b11000 +
b11000 *
#255
1#
#260
0#
b11111010 (
b11111010 0
b11001 $
b11001 +
b11001 *
#265
1#
#270
0#
b100000100 (
b100000100 0
b11010 $
b11010 +
b11010 *
#275
1#
#280
0#
b100001110 (
b100001110 0
b11011 $
b11011 +
b11011 *
#285
1#
#290
0#
b100011000 (
b100011000 0
b11100 $
b11100 +
b11100 *
#295
1#
#300
0#
b100100010 (
b100100010 0
b11101 $
b11101 +
b11101 *
#305
1#
#310
0#
b100101100 (
b100101100 0
b11110 $
b11110 +
b11110 *
#315
1#
#320
0#
b100110110 (
b100110110 0
b11111 $
b11111 +
b11111 *
#325
1#
#330
0#
b1010 !
b1010 -
b1 '
b1 /
b0 "
b0 ,
b0 &
b0 .
0)
b0 *
#335
1#
b11110 !
b11110 -
b11 '
b11 /
b10100 "
b10100 ,
b10 &
b10 .
b10 *
#340
0#
b110010 !
b110010 -
b101 '
b101 /
b101000 "
b101000 ,
b100 &
b100 .
b100 *
#345
1#
b1000110 !
b1000110 -
b111 '
b111 /
b111100 "
b111100 ,
b110 &
b110 .
b110 *
#350
0#
b1011010 !
b1011010 -
b1001 '
b1001 /
b1010000 "
b1010000 ,
b1000 &
b1000 .
b1000 *
#355
1#
b1101110 !
b1101110 -
b1011 '
b1011 /
b1100100 "
b1100100 ,
b1010 &
b1010 .
b1010 *
#360
0#
b10000010 !
b10000010 -
b1101 '
b1101 /
b1111000 "
b1111000 ,
b1100 &
b1100 .
b1100 *
#365
1#
b10010110 !
b10010110 -
b1111 '
b1111 /
b10001100 "
b10001100 ,
b1110 &
b1110 .
b1110 *
#370
0#
b10101010 !
b10101010 -
b10001 '
b10001 /
b10100000 "
b10100000 ,
b10000 &
b10000 .
b10000 *
#375
1#
b10111110 !
b10111110 -
b10011 '
b10011 /
b10110100 "
b10110100 ,
b10010 &
b10010 .
b10010 *
#380
0#
b11010010 !
b11010010 -
b10101 '
b10101 /
b11001000 "
b11001000 ,
b10100 &
b10100 .
b10100 *
#385
1#
b11100110 !
b11100110 -
b10111 '
b10111 /
b11011100 "
b11011100 ,
b10110 &
b10110 .
b10110 *
#390
0#
b11111010 !
b11111010 -
b11001 '
b11001 /
b11110000 "
b11110000 ,
b11000 &
b11000 .
b11000 *
#395
1#
b100001110 !
b100001110 -
b11011 '
b11011 /
b100000100 "
b100000100 ,
b11010 &
b11010 .
b11010 *
#400
0#
b100100010 !
b100100010 -
b11101 '
b11101 /
b100011000 "
b100011000 ,
b11100 &
b11100 .
b11100 *
#405
1#
b100110110 !
b100110110 -
b11111 '
b11111 /
b100101100 "
b100101100 ,
b11110 &
b11110 .
b11110 *
#410
0#
b100000 *
